jutlautil/__init__.py
jutlautil/anchor.py
jutlautil-0.0.5.dist-info/licenses/LICENSE
jutlautil-0.0.5.dist-info/METADATA
jutlautil-0.0.5.dist-info/WHEEL
jutlautil-0.0.5.dist-info/top_level.txt
jutlautil-0.0.5.dist-info/RECORD
