Metadata-Version: 2.4
Name: jutlautil
Version: 0.0.5
Summary: Package for personal utilities
Author-email: Amandeep Jutla <ajutla@amandeepjutla.com>
License: MIT
Project-URL: Homepage, https://github.com/amandeepjutla/jutlautil
Project-URL: Repository, https://github.com/amandeepjutla/jutlautil
Project-URL: Issues, https://github.com/amandeepjutla/jutlautil/issues
Keywords: directory,anchor
Classifier: License :: OSI Approved :: MIT License
Classifier: Programming Language :: Python :: 3
Requires-Python: >=3.7
License-File: LICENSE
Dynamic: license-file
